scoutos/__init__.py
scoutos/client.py
scoutos/collections/__init__.py
scoutos/collections/client.py
scoutos/collections/raw_client.py
scoutos/collections/types/__init__.py
scoutos/collections/types/create_view_request_settings.py
scoutos/collections/types/create_view_request_type.py
scoutos/collections/types/update_view_request_settings.py
scoutos/collections/types/update_view_request_type.py
scoutos/copilots/__init__.py
scoutos/copilots/client.py
scoutos/copilots/raw_client.py
scoutos/core/__init__.py
scoutos/core/api_error.py
scoutos/core/client_wrapper.py
scoutos/core/datetime_utils.py
scoutos/core/file.py
scoutos/core/force_multipart.py
scoutos/core/http_client.py
scoutos/core/http_response.py
scoutos/core/jsonable_encoder.py
scoutos/core/pydantic_utilities.py
scoutos/core/query_encoder.py
scoutos/core/remove_none_from_dict.py
scoutos/core/request_options.py
scoutos/core/serialization.py
scoutos/core/unchecked_base_model.py
scoutos/documents/__init__.py
scoutos/documents/client.py
scoutos/documents/raw_client.py
scoutos/documents/types/__init__.py
scoutos/documents/types/documents_create_request_body.py
scoutos/documents/types/documents_create_request_body_item_value.py
scoutos/documents/types/documents_create_request_body_one_value.py
scoutos/documents/types/documents_create_request_body_zero_value.py
scoutos/documents/types/documents_update_batch_request_body.py
scoutos/documents/types/documents_update_batch_request_body_item_value.py
scoutos/documents/types/documents_update_batch_request_body_one_value.py
scoutos/documents/types/documents_update_batch_request_body_zero_value.py
scoutos/environment.py
scoutos/environments/__init__.py
scoutos/environments/client.py
scoutos/environments/raw_client.py
scoutos/errors/__init__.py
scoutos/errors/unprocessable_entity_error.py
scoutos/integrations/__init__.py
scoutos/integrations/client.py
scoutos/integrations/raw_client.py
scoutos/organizations/__init__.py
scoutos/organizations/client.py
scoutos-0.11.1.dist-info/METADATA
scoutos-0.11.1.dist-info/WHEEL
scoutos-0.11.1.dist-info/RECORD
